mcp_test_kits/__init__.py
mcp_test_kits/__main__.py
mcp_test_kits/config.py
mcp_test_kits/extract_spec.py
mcp_test_kits/server.py
mcp_test_kits/auth/__init__.py
mcp_test_kits/auth/config.py
mcp_test_kits/auth/jwt_handler.py
mcp_test_kits/auth/middleware.py
mcp_test_kits/auth/oauth_endpoints.py
mcp_test_kits/auth/pkce.py
mcp_test_kits/auth/scopes.py
mcp_test_kits/auth/token_store.py
mcp_test_kits/auth/well_known.py
mcp_test_kits/capabilities/__init__.py
mcp_test_kits/capabilities/prompts.py
mcp_test_kits/capabilities/resources.py
mcp_test_kits/capabilities/tools.py
mcp_test_kits/transports/__init__.py
mcp_test_kits/transports/http.py
mcp_test_kits/transports/sse.py
mcp_test_kits/transports/stdio.py
mcp_test_kits-0.0.6.dist-info/METADATA
mcp_test_kits-0.0.6.dist-info/WHEEL
mcp_test_kits-0.0.6.dist-info/entry_points.txt
mcp_test_kits-0.0.6.dist-info/RECORD
