Metadata-Version: 2.4
Name: mcp-test-kits
Version: 0.0.6
Summary: A comprehensive MCP testing server for debugging and testing MCP clients
Author: midodimori
License: MIT
Keywords: ai,llm,mcp,model-context-protocol,testing
Classifier: Development Status :: 4 - Beta
Classifier: Intended Audience :: Developers
Classifier: License :: OSI Approved :: MIT License
Classifier: Programming Language :: Python :: 3
Classifier: Programming Language :: Python :: 3.12
Classifier: Programming Language :: Python :: 3.13
Classifier: Topic :: Software Development :: Testing
Requires-Python: >=3.13
Requires-Dist: fastmcp>=2.0.0
Requires-Dist: pydantic>=2.0
Requires-Dist: pyjwt>=2.8.0
Requires-Dist: starlette>=0.40.0
Requires-Dist: uvicorn>=0.30.0
